marketpanda/__init__.py
marketpanda/build_db_tables.py
marketpanda/cpi_insert.py
marketpanda/daily_price_updates.py
marketpanda/marketpanda.py
marketpanda/marketvault.py
marketpanda/retrieve_historic_prices.py
marketpanda/scrape_snp500_current.py
marketpanda/scrape_snp500_past.py
marketpanda/snp500_insert.py
marketpanda/utils/__init__.py
marketpanda/utils/fileio.py
marketpanda/utils/progress.py
marketpanda/version.py
marketpanda-0.1.8.dist-info/METADATA
marketpanda-0.1.8.dist-info/WHEEL
marketpanda-0.1.8.dist-info/RECORD
