Metadata-Version: 2.1
Name: marketpanda
Version: 0.1.8
Summary: MarketVault access library
License: MIT
Author: Fayssal El Mofatiche
Author-email: fayssal.elmofatiche@dnbf.tech
Requires-Python: >=3.11,<3.13
Classifier: License :: OSI Approved :: MIT License
Classifier: Programming Language :: Python :: 3
Classifier: Programming Language :: Python :: 3.11
Requires-Dist: cpi (>=1.0.21,<2.0.0)
Requires-Dist: gdown (>=4.7.1,<5.0.0)
Requires-Dist: pandas (>=2.1.1,<3.0.0)
Requires-Dist: requests (>=2.31.0,<3.0.0)
